jira_mcp/__init__.py
jira_mcp/__main__.py
jira_mcp/attachment_downloader.py
jira_mcp/cli.py
jira_mcp/config.py
jira_mcp/server.py
jira_mcp/scripts/__init__.py
jira_mcp/scripts/download_all_attachments.py
jira_mcp/scripts/extract_attachment.py
g7_jira_mcp-0.1.3.dist-info/METADATA
g7_jira_mcp-0.1.3.dist-info/WHEEL
g7_jira_mcp-0.1.3.dist-info/entry_points.txt
g7_jira_mcp-0.1.3.dist-info/licenses/LICENSE
g7_jira_mcp-0.1.3.dist-info/RECORD
