Metadata-Version: 2.4
Name: g7-jira-mcp
Version: 0.1.3
Summary: JIRA MCP for querying JIRA details and lists
Project-URL: Homepage, https://github.com/YOUR_USERNAME/g7-jira-mcp
Project-URL: Bug Tracker, https://github.com/YOUR_USERNAME/g7-jira-mcp/issues
Project-URL: Documentation, https://github.com/YOUR_USERNAME/g7-jira-mcp#readme
Author-email: Your Name <your-email@example.com>
License: MIT
License-File: LICENSE
Keywords: cursor,fastmcp,jira,mcp
Classifier: Development Status :: 4 - Beta
Classifier: Intended Audience :: Developers
Classifier: License :: OSI Approved :: MIT License
Classifier: Programming Language :: Python :: 3
Classifier: Programming Language :: Python :: 3.10
Classifier: Programming Language :: Python :: 3.11
Classifier: Programming Language :: Python :: 3.12
Classifier: Topic :: Software Development :: Libraries :: Python Modules
Requires-Python: <3.13,>=3.10
Requires-Dist: fastapi>=0.110.0
Requires-Dist: jira>=3.8.0
Requires-Dist: mcp>=1.9.0
Requires-Dist: playwright>=1.40.0
Requires-Dist: pydantic>=2.11.0
Requires-Dist: python-dotenv>=1.1.0
Requires-Dist: requests>=2.32.0
Requires-Dist: typing-extensions>=4.13.0
Requires-Dist: uvicorn>=0.34.0
Provides-Extra: dev
Requires-Dist: black>=23.0.0; extra == 'dev'
Requires-Dist: isort>=5.0.0; extra == 'dev'
Requires-Dist: pytest-asyncio>=0.21.0; extra == 'dev'
Requires-Dist: pytest-cov>=4.0.0; extra == 'dev'
Requires-Dist: pytest-mock>=3.10.0; extra == 'dev'
Requires-Dist: pytest>=7.0.0; extra == 'dev'
